atommic/__init__.py
atommic/constants.py
atommic/package_info.py
atommic/cli/__init__.py
atommic/cli/launch.py
atommic/collections/__init__.py
atommic/collections/common/__init__.py
atommic/collections/common/callbacks/__init__.py
atommic/collections/common/callbacks/callbacks.py
atommic/collections/common/callbacks/ema.py
atommic/collections/common/data/__init__.py
atommic/collections/common/data/mri_loader.py
atommic/collections/common/data/subsample.py
atommic/collections/common/losses/__init__.py
atommic/collections/common/losses/aggregator.py
atommic/collections/common/losses/wasserstein.py
atommic/collections/common/metrics/__init__.py
atommic/collections/common/metrics/global_average_loss_metric.py
atommic/collections/common/nn/__init__.py
atommic/collections/common/nn/base.py
atommic/collections/common/parts/__init__.py
atommic/collections/common/parts/coil_sensitivity_maps.py
atommic/collections/common/parts/fft.py
atommic/collections/common/parts/patch_utils.py
atommic/collections/common/parts/transforms.py
atommic/collections/common/parts/utils.py
atommic/collections/motioncorrection/__init__.py
atommic/collections/motioncorrection/parts/__init__.py
atommic/collections/motioncorrection/parts/motionsimulation.py
atommic/collections/multitask/__init__.py
atommic/collections/multitask/rs/__init__.py
atommic/collections/multitask/rs/data/__init__.py
atommic/collections/multitask/rs/data/mrirs_loader.py
atommic/collections/multitask/rs/nn/__init__.py
atommic/collections/multitask/rs/nn/base.py
atommic/collections/multitask/rs/nn/idslr.py
atommic/collections/multitask/rs/nn/idslr_unet.py
atommic/collections/multitask/rs/nn/mtlrs.py
atommic/collections/multitask/rs/nn/recseg_unet.py
atommic/collections/multitask/rs/nn/segnet.py
atommic/collections/multitask/rs/nn/seranet.py
atommic/collections/multitask/rs/nn/idslr_base/__init__.py
atommic/collections/multitask/rs/nn/idslr_base/idslr_block.py
atommic/collections/multitask/rs/nn/mtlrs_base/__init__.py
atommic-1.0.1.dist-info/LICENSE
atommic-1.0.1.dist-info/METADATA
atommic-1.0.1.dist-info/WHEEL
atommic-1.0.1.dist-info/entry_points.txt
atommic-1.0.1.dist-info/top_level.txt
atommic-1.0.1.dist-info/RECORD
