Metadata-Version: 2.1
Name: atommic
Version: 1.0.1
Summary: Advanced Toolbox for Multitask Medical Imaging Consistency (ATOMMIC)
Home-page: https://github.com/wdika/atommic
Download-URL: https://github.com/wdika/atommic/releases
Author: Dimitris Karkalousos
Author-email: d.karkalousos@amsterdamumc.nl
Maintainer: Dimitris Karkalousos
Maintainer-email: d.karkalousos@amsterdamumc.nl
License: Apache-2.0 License
Keywords: deep-learning,medical-imaging,mri,quantitative-imaging,medical-image-processing,medical-image-analysis
Classifier: Development Status :: 5 - Production/Stable
Classifier: Intended Audience :: Developers
Classifier: Intended Audience :: Science/Research
Classifier: Intended Audience :: Information Technology
Classifier: Topic :: Scientific/Engineering
Classifier: Topic :: Scientific/Engineering :: Artificial Intelligence
Classifier: Topic :: Scientific/Engineering :: Physics
Classifier: Topic :: Software Development :: Libraries
Classifier: Topic :: Software Development :: Libraries :: Python Modules
Classifier: Topic :: Utilities
Classifier: License :: OSI Approved :: Apache Software License
Classifier: Programming Language :: Python :: 3.10
Classifier: Environment :: Console
Classifier: Natural Language :: English
Classifier: Operating System :: OS Independent
Requires-Python: >=3.10, <=3.12
License-File: LICENSE
Requires-Dist: defusedxml >=0.7.1
Requires-Dist: einops >=0.5.0
Requires-Dist: h5py ==3.9.0
Requires-Dist: huggingface-hub
Requires-Dist: hydra-core <=1.3.2,>1.3
Requires-Dist: nibabel ==5.1.0
Requires-Dist: numba
Requires-Dist: numpy <=1.24.2,>=1.22
Requires-Dist: omegaconf <=2.3
Requires-Dist: onnx >=1.11.0
Requires-Dist: onnxruntime ==1.15.1
Requires-Dist: pytest ==7.4.0
Requires-Dist: python-dateutil
Requires-Dist: pytorch-lightning <=2.0.7,>=2.0.0
Requires-Dist: runstats >=2.0.0
Requires-Dist: scikit-image ==0.21.0
Requires-Dist: setuptools ==65.5.1
Requires-Dist: tensorboard
Requires-Dist: torch <2.1.0,>=2.0.0
Requires-Dist: torchmetrics >=0.11.0
Requires-Dist: tqdm
Requires-Dist: wandb ==0.15.8
Requires-Dist: wget >=3.2
Requires-Dist: wrapt >=1.13.3
